{"filename":"db.json","collections":[{"name":"customers","data":[{"customer":"Sunrise Bank","API_Key":"AIzaSyAWwP5yH9Hke0FQkwEUujx-L8QelE27ZpY","Type":"atm","Language":"en","meta":{"revision":0,"created":1532431430401,"version":0},"$loki":1},{"customer":"Happy Credit Union","API_Key":"AIzaSyAYaNzyQoSDKW0FIUxhEgUEsmPic9XqtPU","Type":"bank","Language":"es","meta":{"revision":0,"created":1532431430401,"version":0},"$loki":2},{"customer":"Paris FCU","API_Key":"AIzaSyAdAnwAfMAEDU3igUPKq_v8QrapgzyNHT4","Type":"all","Language":"fr","meta":{"revision":0,"created":1532431430401,"version":0},"$loki":3}],"idIndex":[1,2,3],"binaryIndices":{},"constraints":null,"uniqueNames":[],"transforms":{},"objType":"customers","dirty":false,"cachedIndex":null,"cachedBinaryIndex":null,"cachedData":null,"adaptiveBinaryIndices":true,"transactional":false,"cloneObjects":false,"cloneMethod":"parse-stringify","asyncListeners":false,"disableMeta":false,"disableChangesApi":true,"disableDeltaChangesApi":true,"autoupdate":false,"serializableIndices":true,"ttl":null,"maxId":3,"DynamicViews":[],"events":{"insert":[],"update":[],"pre-insert":[],"pre-update":[],"close":[],"flushbuffer":[],"error":[],"delete":[null],"warning":[null]},"changes":[]}],"databaseVersion":1.5,"engineVersion":1.5,"autosave":true,"autosaveInterval":4000,"autosaveHandle":null,"throttledSaves":true,"options":{"autoload":true,"autosave":true,"autosaveInterval":4000,"serializationMethod":"normal","destructureDelimiter":"$<\n","recursiveWait":true,"recursiveWaitLimit":false,"recursiveWaitLimitDuration":2000,"started":1532431430399},"persistenceMethod":"fs","persistenceAdapter":null,"verbose":false,"events":{"init":[null],"loaded":[],"flushChanges":[],"close":[],"changes":[],"warning":[]},"ENV":"NODEJS"}